pyConic/__init__.py
pyConic/conic.py
pyConic-0.1.1.dist-info/LICENSE
pyConic-0.1.1.dist-info/METADATA
pyConic-0.1.1.dist-info/WHEEL
pyConic-0.1.1.dist-info/top_level.txt
pyConic-0.1.1.dist-info/RECORD
